[
    {
        "show": "What's New, Scooby-Doo?: What's New Scooby-Doo?: Season 2: Mummy Scares Best",
        "date": "2020-01-02T05:00:00.000Z"
    },
    {
        "show": "What's New, Scooby-Doo?: What's New Scooby-Doo?: Season 2: Big Appetite in Little Tokyo",
        "date": "2020-01-02T05:00:00.000Z"
    },
    {
        "show": "What's New, Scooby-Doo?: What's New Scooby-Doo?: Season 1: The Unnatural",
        "date": "2020-01-02T05:00:00.000Z"
    },
    {
        "show": "What's New, Scooby-Doo?: What's New Scooby-Doo?: Season 1: Pompeii and Circumstance",
        "date": "2020-01-01T05:00:00.000Z"
    },
    {
        "show": "What's New, Scooby-Doo?: What's New Scooby-Doo?: Season 1: Lights! Camera! Mayhem!",
        "date": "2020-01-01T05:00:00.000Z"
    },
    {
        "show": "What's New, Scooby-Doo?: What's New Scooby-Doo?: Season 1: Toy Scary Boo",
        "date": "2020-01-01T05:00:00.000Z"
    },
    {
        "show": "Scooby-Doo!: Mystery Incorporated: Season 2: Come Undone",
        "date": "2020-01-01T05:00:00.000Z"
    },
    {
        "show": "Scooby-Doo!: Mystery Incorporated: Season 2: Through the Curtain",
        "date": "2020-01-01T05:00:00.000Z"
    },
    {
        "show": "Scooby-Doo!: Mystery Incorporated: Season 2: Gates of Gloom",
        "date": "2020-01-01T05:00:00.000Z"
    },
    {
        "show": "Scooby-Doo!: Mystery Incorporated: Season 2: Dark Night of the Hunters",
        "date": "2019-12-31T05:00:00.000Z"
    },
    {
        "show": "Scooby-Doo!: Mystery Incorporated: Season 2: Nightmare in Red",
        "date": "2019-12-30T05:00:00.000Z"
    },
    {
        "show": "Scooby-Doo!: Mystery Incorporated: Season 2: The Man in the Mirror",
        "date": "2019-12-30T05:00:00.000Z"
    },
    {
        "show": "Scooby-Doo!: Mystery Incorporated: Season 2: Stand and Deliver",
        "date": "2019-12-30T05:00:00.000Z"
    },
    {
        "show": "Scooby-Doo!: Mystery Incorporated: Season 2: The Devouring",
        "date": "2019-12-30T05:00:00.000Z"
    },
    {
        "show": "What's New, Scooby-Doo?: What's New Scooby-Doo?: Season 1: A Scooby-Doo! Christmas",
        "date": "2019-12-29T05:00:00.000Z"
    },
    {
        "show": "What's New, Scooby-Doo?: What's New Scooby-Doo?: Season 1: She Sees Sea Monsters by the Sea Shore",
        "date": "2019-12-29T05:00:00.000Z"
    },
    {
        "show": "What's New, Scooby-Doo?: What's New Scooby-Doo?: Season 1: Safari, So Goodi",
        "date": "2019-12-29T05:00:00.000Z"
    },
    {
        "show": "Scooby-Doo!: Mystery Incorporated: Season 2: Dance of the Undead",
        "date": "2019-12-29T05:00:00.000Z"
    },
    {
        "show": "Scooby-Doo!: Mystery Incorporated: Season 2: The Horrible Herd",
        "date": "2019-12-29T05:00:00.000Z"
    },
    {
        "show": "Scooby-Doo!: Mystery Incorporated: Season 2: Aliens Among Us",
        "date": "2019-12-29T05:00:00.000Z"
    },
    {
        "show": "Scooby-Doo!: Mystery Incorporated: Season 2: Theater of Doom",
        "date": "2019-12-29T05:00:00.000Z"
    },
    {
        "show": "Scooby-Doo!: Mystery Incorporated: Season 2: Heart of Evil",
        "date": "2019-12-29T05:00:00.000Z"
    },
    {
        "show": "What's New, Scooby-Doo?: What's New Scooby-Doo?: Season 1: Roller Ghoster Ride!",
        "date": "2019-12-29T05:00:00.000Z"
    },
    {
        "show": "What's New, Scooby-Doo?: What's New Scooby-Doo?: Season 1: Riva Ras Regas",
        "date": "2019-12-29T05:00:00.000Z"
    },
    {
        "show": "Scooby-Doo!: Mystery Incorporated: Season 2: Wrath of the Krampus",
        "date": "2019-12-28T05:00:00.000Z"
    },
    {
        "show": "Scooby-Doo!: Mystery Incorporated: Season 2: Scarebear",
        "date": "2019-12-28T05:00:00.000Z"
    },
    {
        "show": "Scooby-Doo!: Mystery Incorporated: Season 2: The Midnight Zone",
        "date": "2019-12-28T05:00:00.000Z"
    },
    {
        "show": "Scooby-Doo!: Mystery Incorporated: Season 2: Night Terrors",
        "date": "2019-12-28T05:00:00.000Z"
    },
    {
        "show": "Scooby-Doo!: Mystery Incorporated: Season 2: Grim Judgment",
        "date": "2019-12-28T05:00:00.000Z"
    },
    {
        "show": "Scooby-Doo!: Mystery Incorporated: Season 2: Night on Haunted Mountain",
        "date": "2019-12-27T05:00:00.000Z"
    },
    {
        "show": "Scooby-Doo!: Mystery Incorporated: Season 2: The Gathering Gloom",
        "date": "2019-12-27T05:00:00.000Z"
    },
    {
        "show": "Scooby-Doo!: Mystery Incorporated: Season 2: Art of Darkness!",
        "date": "2019-12-26T05:00:00.000Z"
    },
    {
        "show": "Scooby-Doo!: Mystery Incorporated: Season 2: The Hodag of Horror",
        "date": "2019-12-26T05:00:00.000Z"
    },
    {
        "show": "Scooby-Doo!: Mystery Incorporated: Season 2: Web of the Dreamweaver!",
        "date": "2019-12-26T05:00:00.000Z"
    },
    {
        "show": "Scooby-Doo!: Mystery Incorporated: Season 2: The Night the Clown Cried II - Tears of Doom!",
        "date": "2019-12-26T05:00:00.000Z"
    },
    {
        "show": "Scooby-Doo!: Mystery Incorporated: Season 2: The House of the Nightmare Witch",
        "date": "2019-12-25T05:00:00.000Z"
    },
    {
        "show": "Scooby-Doo!: Mystery Incorporated: Season 2: The Night the Clown Cried",
        "date": "2019-12-25T05:00:00.000Z"
    },
    {
        "show": "Scooby-Doo!: Mystery Incorporated: Season 1: All Fear the Freak",
        "date": "2019-12-25T05:00:00.000Z"
    },
    {
        "show": "Scooby-Doo!: Mystery Incorporated: Season 1: Pawn of Shadows",
        "date": "2019-12-25T05:00:00.000Z"
    },
    {
        "show": "Scooby-Doo!: Mystery Incorporated: Season 1: Dead Justice",
        "date": "2019-12-25T05:00:00.000Z"
    },
    {
        "show": "Scooby-Doo!: Mystery Incorporated: Season 1: A Haunting In Crystal Cove",
        "date": "2019-12-25T05:00:00.000Z"
    },
    {
        "show": "Scooby-Doo!: Mystery Incorporated: Season 1: Attack of the Headless Horror",
        "date": "2019-12-25T05:00:00.000Z"
    },
    {
        "show": "Scooby-Doo!: Mystery Incorporated: Season 1: Menace of the Manticore",
        "date": "2019-12-25T05:00:00.000Z"
    },
    {
        "show": "Scooby-Doo!: Mystery Incorporated: Season 1: The Siren's Song",
        "date": "2019-12-25T05:00:00.000Z"
    },
    {
        "show": "Scooby-Doo!: Mystery Incorporated: Season 1: Night Fright",
        "date": "2019-12-25T05:00:00.000Z"
    },
    {
        "show": "Scooby-Doo!: Mystery Incorporated: Season 1: The Dragon's Secret",
        "date": "2019-12-25T05:00:00.000Z"
    },
    {
        "show": "Scooby-Doo!: Mystery Incorporated: Season 1: Escape from Mystery Manor",
        "date": "2019-12-25T05:00:00.000Z"
    },
    {
        "show": "Scooby-Doo!: Mystery Incorporated: Season 1: Where Walks Aphrodite",
        "date": "2019-12-25T05:00:00.000Z"
    },
    {
        "show": "Scooby-Doo!: Mystery Incorporated: Season 1: The Wild Brood",
        "date": "2019-12-25T05:00:00.000Z"
    },
    {
        "show": "Scooby-Doo!: Mystery Incorporated: Season 1: Mystery Solvers Club State Finals",
        "date": "2019-12-25T05:00:00.000Z"
    },
    {
        "show": "Scooby-Doo!: Mystery Incorporated: Season 1: When the Cicada Calls",
        "date": "2019-12-25T05:00:00.000Z"
    },
    {
        "show": "Scooby-Doo!: Mystery Incorporated: Season 1: The Shrieking Madness",
        "date": "2019-12-25T05:00:00.000Z"
    },
    {
        "show": "Scooby-Doo!: Mystery Incorporated: Season 1: The Secret Serum",
        "date": "2019-12-25T05:00:00.000Z"
    },
    {
        "show": "Scooby-Doo!: Mystery Incorporated: Season 1: Howl of the Fright Hound",
        "date": "2019-12-24T05:00:00.000Z"
    },
    {
        "show": "Scooby-Doo!: Mystery Incorporated: Season 1: Battle of the Humungonauts",
        "date": "2019-12-24T05:00:00.000Z"
    },
    {
        "show": "Scooby-Doo!: Mystery Incorporated: Season 1: The Grasp of the Gnome",
        "date": "2019-12-24T05:00:00.000Z"
    },
    {
        "show": "Scooby-Doo!: Mystery Incorporated: Season 1: In Fear of the Phantom",
        "date": "2019-12-23T05:00:00.000Z"
    },
    {
        "show": "Scooby-Doo!: Mystery Incorporated: Season 1: The Legend of Alice May",
        "date": "2019-12-23T05:00:00.000Z"
    },
    {
        "show": "Scooby-Doo!: Mystery Incorporated: Season 1: The Song of Mystery",
        "date": "2019-12-23T05:00:00.000Z"
    },
    {
        "show": "Scooby-Doo!: Mystery Incorporated: Season 1: Revenge of the Man Crab",
        "date": "2019-12-23T05:00:00.000Z"
    },
    {
        "show": "Scooby-Doo!: Mystery Incorporated: Season 1: The Secret of the Ghost Rig",
        "date": "2019-12-22T05:00:00.000Z"
    },
    {
        "show": "Scooby-Doo!: Mystery Incorporated: Season 1: The Creeping Creatures",
        "date": "2019-12-22T05:00:00.000Z"
    },
    {
        "show": "Scooby-Doo!: Mystery Incorporated: Season 1: Beware the Beast from Below",
        "date": "2019-12-22T05:00:00.000Z"
    },
    {
        "show": "What's New, Scooby-Doo?: What's New Scooby-Doo?: Season 1: It's Mean, It's Green, It's The Mystery Machine",
        "date": "2019-12-21T05:00:00.000Z"
    },
    {
        "show": "What's New, Scooby-Doo?: What's New Scooby-Doo?: Season 1: Big Scare in the Big Easy",
        "date": "2019-12-21T05:00:00.000Z"
    },
    {
        "show": "What's New, Scooby-Doo?: What's New Scooby-Doo?: Season 1: Space Ape at the Cape",
        "date": "2019-12-20T05:00:00.000Z"
    },
    {
        "show": "What's New, Scooby-Doo?: What's New Scooby-Doo?: Season 1: 3-D Struction",
        "date": "2019-12-20T05:00:00.000Z"
    },
    {
        "show": "What's New, Scooby-Doo?: What's New Scooby-Doo?: Season 1: There's No Creature Like Snow Creature",
        "date": "2019-12-20T05:00:00.000Z"
    },
    {
        "show": "LEGO Marvel Super Heroes: Guardians of the Galaxy",
        "date": "2019-12-14T05:00:00.000Z"
    },
    {
        "show": "The Spooky Tale of Captain Underpants Hack-a-ween",
        "date": "2019-12-14T05:00:00.000Z"
    },
    {
        "show": "Kicko & Super Speedo: Season 1: Episode 2",
        "date": "2019-12-07T05:00:00.000Z"
    },
    {
        "show": "Kicko & Super Speedo: Season 1: Episode 1",
        "date": "2019-12-07T05:00:00.000Z"
    },
    {
        "show": "Kicko & Super Speedo: Season 1: Episode 7",
        "date": "2019-12-05T05:00:00.000Z"
    },
    {
        "show": "Kicko & Super Speedo: Season 1: Episode 6",
        "date": "2019-12-05T05:00:00.000Z"
    },
    {
        "show": "Kicko & Super Speedo: Season 1: Episode 5",
        "date": "2019-12-05T05:00:00.000Z"
    },
    {
        "show": "Kicko & Super Speedo: Season 1: Episode 4",
        "date": "2019-12-05T05:00:00.000Z"
    },
    {
        "show": "Teenage Mutant Ninja Turtles",
        "date": "2019-12-04T05:00:00.000Z"
    },
    {
        "show": "Inspector Gadget: Season 4: The Missionball Ball / Tell Me What Sphinx",
        "date": "2019-11-20T05:00:00.000Z"
    },
    {
        "show": "Monster House",
        "date": "2019-11-17T05:00:00.000Z"
    },
    {
        "show": "The Epic Tales of Captain Underpants: Season 1: Captain Underpants and the Dreadful Debacle of DJ Drowsy Drawers",
        "date": "2019-11-15T05:00:00.000Z"
    },
    {
        "show": "The Epic Tales of Captain Underpants: Season 1: Captain Underpants and the Frenzied Farts of Flabby Flabulous",
        "date": "2019-11-15T05:00:00.000Z"
    },
    {
        "show": "Inspector Gadget: Season 1: My Gadget Will Go On / The Gadgetator",
        "date": "2019-11-13T05:00:00.000Z"
    },
    {
        "show": "Inspector Gadget: Season 1: Collider Scope / She Got Dangerous Game",
        "date": "2019-11-13T05:00:00.000Z"
    },
    {
        "show": "Power Rangers Beast Morphers: Season 1: End of the Road",
        "date": "2019-11-10T05:00:00.000Z"
    },
    {
        "show": "Power Rangers Beast Morphers: Season 1: Beasts Unleashed",
        "date": "2019-11-10T05:00:00.000Z"
    },
    {
        "show": "Inspector Gadget: Season 1: Gadget 2.0: Part 1 / Gadget 2.0: Part 2",
        "date": "2019-11-10T05:00:00.000Z"
    },
    {
        "show": "Inspector Gadget: Season 2: WereBrain of London / Airhead to the Throne",
        "date": "2019-11-10T05:00:00.000Z"
    },
    {
        "show": "Power Rangers Beast Morphers: Season 1: Taking Care of Business",
        "date": "2019-11-10T05:00:00.000Z"
    },
    {
        "show": "Power Rangers Beast Morphers: Season 1: Digital Deception",
        "date": "2019-11-09T05:00:00.000Z"
    },
    {
        "show": "Power Rangers Beast Morphers: Season 1: Evox’s Revenge",
        "date": "2019-11-09T05:00:00.000Z"
    },
    {
        "show": "LEGO Jurassic World: The Indominus Escape",
        "date": "2019-11-09T05:00:00.000Z"
    },
    {
        "show": "Ghost Patrol",
        "date": "2019-11-06T05:00:00.000Z"
    },
    {
        "show": "LEGO Marvel Super Heroes: Avengers Reassembled!",
        "date": "2019-10-29T04:00:00.000Z"
    },
    {
        "show": "Trick or Treaters",
        "date": "2019-10-08T04:00:00.000Z"
    },
    {
        "show": "DC Super Hero Girls: Season 1: #SweetJustice: Part 2",
        "date": "2019-09-30T04:00:00.000Z"
    },
    {
        "show": "DC Super Hero Girls: Season 1: #SweetJustice: Part 1",
        "date": "2019-09-30T04:00:00.000Z"
    },
    {
        "show": "Lego DC Comics: Batman Be-Leaguered",
        "date": "2019-09-30T04:00:00.000Z"
    },
    {
        "show": "Super Wings: Season 2: It Came From Hong Kong",
        "date": "2019-09-30T04:00:00.000Z"
    },
    {
        "show": "Power Rangers Ninja Steel: Season 2: Tough Love",
        "date": "2019-09-25T04:00:00.000Z"
    },
    {
        "show": "Power Rangers Ninja Steel: Season 2: Moment of Truth",
        "date": "2019-09-25T04:00:00.000Z"
    },
    {
        "show": "Power Rangers Ninja Steel: Season 2: The Poisy Show",
        "date": "2019-09-25T04:00:00.000Z"
    },
    {
        "show": "Pac's Scary Halloween",
        "date": "2019-09-19T04:00:00.000Z"
    },
    {
        "show": "Dragons: Race to the Edge: Season 1: Big Man on Berk",
        "date": "2019-09-15T04:00:00.000Z"
    },
    {
        "show": "Dragons: Race to the Edge: Season 1: When Darkness Falls",
        "date": "2019-09-15T04:00:00.000Z"
    },
    {
        "show": "Goosebumps: Specials: The Werewolf of Fever Swamp - Part 2",
        "date": "2019-09-13T04:00:00.000Z"
    },
    {
        "show": "Goosebumps: Specials: The Haunted Mask - Part 2",
        "date": "2019-09-13T04:00:00.000Z"
    },
    {
        "show": "Goosebumps 2: Haunted Halloween",
        "date": "2019-09-13T04:00:00.000Z"
    },
    {
        "show": "Dr. Seuss' The Grinch",
        "date": "2019-09-07T04:00:00.000Z"
    },
    {
        "show": "Goosebumps: Season 3: Don't Wake Mummy",
        "date": "2019-09-03T04:00:00.000Z"
    },
    {
        "show": "Goosebumps: Season 2: You Can't Scare Me",
        "date": "2019-09-03T04:00:00.000Z"
    },
    {
        "show": "Goosebumps: Season 1: Piano Lessons Can Be Murder",
        "date": "2019-09-03T04:00:00.000Z"
    },
    {
        "show": "Goosebumps: Specials: Welcome to the Dead House - Part 2",
        "date": "2019-09-03T04:00:00.000Z"
    },
    {
        "show": "Goosebumps: Season 3: Perfect School - Part 2",
        "date": "2019-09-03T04:00:00.000Z"
    },
    {
        "show": "Goosebumps: Season 3: One Day at Horrorland - Part 2",
        "date": "2019-09-02T04:00:00.000Z"
    },
    {
        "show": "Goosebumps: Season 3: One Day at Horrorland - Part 1",
        "date": "2019-09-02T04:00:00.000Z"
    },
    {
        "show": "Goosebumps: Season 3: Shocker on Shock Street",
        "date": "2019-09-02T04:00:00.000Z"
    },
    {
        "show": "Goosebumps: Season 1: The Girl Who Cried Monster",
        "date": "2019-09-02T04:00:00.000Z"
    },
    {
        "show": "Goosebumps: Season 3: My Best Friend is Invisible",
        "date": "2019-09-02T04:00:00.000Z"
    },
    {
        "show": "Goosebumps: Season 2: Be Careful What You Wish For",
        "date": "2019-09-01T04:00:00.000Z"
    },
    {
        "show": "Goosebumps: Season 2: The Headless Ghost",
        "date": "2019-09-01T04:00:00.000Z"
    },
    {
        "show": "Goosebumps: Season 1: Say Cheese and Die",
        "date": "2019-09-01T04:00:00.000Z"
    },
    {
        "show": "Goosebumps: Season 1: Night of the Living Dummy 2",
        "date": "2019-09-01T04:00:00.000Z"
    },
    {
        "show": "The Haunted House: The Secret of the Ghost Ball: Season 1: The Spectral Sentinel",
        "date": "2019-08-31T04:00:00.000Z"
    },
    {
        "show": "The Haunted House: The Secret of the Ghost Ball: Season 1: The Vampire King",
        "date": "2019-08-31T04:00:00.000Z"
    },
    {
        "show": "The Haunted House: The Secret of the Ghost Ball: Season 1: The Malediction Malfunction",
        "date": "2019-08-31T04:00:00.000Z"
    },
    {
        "show": "The Haunted House: The Secret of the Ghost Ball: Season 1: Shinbi Apartment – Doomsday (Part Two)",
        "date": "2019-08-31T04:00:00.000Z"
    },
    {
        "show": "The Haunted House: The Secret of the Ghost Ball: Season 1: The Terrifying Temptation of the Shadow Ghost",
        "date": "2019-08-31T04:00:00.000Z"
    },
    {
        "show": "Bat Pat: Season 1: Footloose / Just Desserts",
        "date": "2019-08-27T04:00:00.000Z"
    },
    {
        "show": "Bat Pat: Season 1: A Big Stink / Eye of the Beholder",
        "date": "2019-08-27T04:00:00.000Z"
    },
    {
        "show": "Bat Pat: Season 1: Gnome Alone / How to Restrain Your Dragon",
        "date": "2019-08-27T04:00:00.000Z"
    },
    {
        "show": "Bat Pat: Season 1: Ghost of a Chance / Sealed with a Curse",
        "date": "2019-08-27T04:00:00.000Z"
    },
    {
        "show": "Bat Pat: Season 1: Over the Rainbow / Ocean's Roar",
        "date": "2019-08-27T04:00:00.000Z"
    },
    {
        "show": "Bat Pat: Season 1: Frozen to the Bones / Puppy Love",
        "date": "2019-08-26T04:00:00.000Z"
    },
    {
        "show": "Bat Pat: Season 1: Dream a Little Dream / Toothless Terror",
        "date": "2019-08-25T04:00:00.000Z"
    },
    {
        "show": "Bat Pat: Season 1: A Haunting Celebration / Seeing Double",
        "date": "2019-08-25T04:00:00.000Z"
    },
    {
        "show": "Bat Pat: Season 1: Tooth or Consequences / Two Heads Aren't Better",
        "date": "2019-08-25T04:00:00.000Z"
    },
    {
        "show": "Bat Pat: Season 1: Love at First Fright / Such a Fright",
        "date": "2019-08-25T04:00:00.000Z"
    },
    {
        "show": "Bat Pat: Season 1: An Uncomfortable Situation / The Lady in the Mirror",
        "date": "2019-08-20T04:00:00.000Z"
    },
    {
        "show": "Bat Pat: Season 1: Survival of the Trolliest / Howl at the Moon",
        "date": "2019-08-20T04:00:00.000Z"
    },
    {
        "show": "Bat Pat: Season 1: Cookie Crumbles / Nothing to Laugh At",
        "date": "2019-08-20T04:00:00.000Z"
    },
    {
        "show": "Bat Pat: Season 1: A Haunting Problem / Moonstruck",
        "date": "2019-08-20T04:00:00.000Z"
    },
    {
        "show": "Bat Pat: Season 1: The Voodoo That You Do / Kitty Cat Caper",
        "date": "2019-08-20T04:00:00.000Z"
    },
    {
        "show": "Bat Pat: Season 1: Wail of a Tale / Two Big Left Feet",
        "date": "2019-08-20T04:00:00.000Z"
    },
    {
        "show": "Bat Pat: Season 1: Something's Fishy / Pirates Ahoy",
        "date": "2019-08-20T04:00:00.000Z"
    },
    {
        "show": "Bat Pat: Season 1: Thing Under the Bed / Monster Jam",
        "date": "2019-08-20T04:00:00.000Z"
    },
    {
        "show": "Bat Pat: Season 1: Boil, Bubble, a Witch in Trouble / Headless House Guest",
        "date": "2019-08-18T04:00:00.000Z"
    },
    {
        "show": "Bat Pat: Season 1: Having a Ball / Queen of the Monkeys",
        "date": "2019-08-18T04:00:00.000Z"
    },
    {
        "show": "Bat Pat: Season 1: Unbearable / The Chosen Martin",
        "date": "2019-08-18T04:00:00.000Z"
    },
    {
        "show": "Bat Pat: Season 1: Scared Stiff / Be Your Elf",
        "date": "2019-08-18T04:00:00.000Z"
    },
    {
        "show": "Bat Pat: Season 1: Slip, Slide and Away / Romeo and Zombiet",
        "date": "2019-08-17T04:00:00.000Z"
    },
    {
        "show": "Bat Pat: Season 1: Just My Luck / Please Don't Make a Wish",
        "date": "2019-08-17T04:00:00.000Z"
    },
    {
        "show": "The Haunted House: The Secret of the Ghost Ball: Season 1: The Mystifying and Malevolent Maze!",
        "date": "2019-08-12T04:00:00.000Z"
    },
    {
        "show": "R.L. Stine's Mostly Ghostly: One Night in Doom House",
        "date": "2019-08-11T04:00:00.000Z"
    },
    {
        "show": "The Dark Crystal",
        "date": "2019-08-11T04:00:00.000Z"
    },
    {
        "show": "The Haunted House: The Secret of the Ghost Ball: Season 1: The Rise of the Underground Nation",
        "date": "2019-08-11T04:00:00.000Z"
    },
    {
        "show": "The Haunted House: The Secret of the Ghost Ball: Season 1: Storm of the Straw Ghost",
        "date": "2019-08-11T04:00:00.000Z"
    },
    {
        "show": "The Haunted House: The Secret of the Ghost Ball: Season 1: The Enticing Entrapment of Ethra",
        "date": "2019-08-11T04:00:00.000Z"
    },
    {
        "show": "The Haunted House: The Secret of the Ghost Ball: Season 1: The Sinister Strike of the Spider Ghost!",
        "date": "2019-08-11T04:00:00.000Z"
    },
    {
        "show": "PJ Masks: Season 1: Catboy VS. Robo-Cat / Owlette and the Giving Owl",
        "date": "2019-08-09T04:00:00.000Z"
    },
    {
        "show": "PJ Masks: Season 1: Speak UP, Gekko! / Catboy and Master Fang's Sword",
        "date": "2019-08-09T04:00:00.000Z"
    },
    {
        "show": "The Haunted House: The Secret of the Ghost Ball: Season 1: The Hair-Raising Tale of the Homunculus!",
        "date": "2019-08-04T04:00:00.000Z"
    },
    {
        "show": "The Haunted House: The Secret of the Ghost Ball: Season 1: The Frightening Fable of the Flower of Death!",
        "date": "2019-08-04T04:00:00.000Z"
    },
    {
        "show": "The Haunted House: The Secret of the Ghost Ball: Season 1: The Horrifying Game of Hide and Seek",
        "date": "2019-08-04T04:00:00.000Z"
    },
    {
        "show": "The Haunted House: The Secret of the Ghost Ball: Season 1: The Spine-Chilling Story of the Skeleton Ghost!",
        "date": "2019-08-03T04:00:00.000Z"
    },
    {
        "show": "The Epic Tales of Captain Underpants: Season 1: Captain Underpants and the Costly Conundrum of the Calamitous Claylossus",
        "date": "2019-07-28T04:00:00.000Z"
    },
    {
        "show": "The Haunted House: The Secret of the Ghost Ball: Season 1: The Mystery of the Marionette Queen",
        "date": "2019-07-28T04:00:00.000Z"
    },
    {
        "show": "The Haunted House: The Secret of the Ghost Ball: Season 1: The Nightmare of the No-Face Ghost",
        "date": "2019-07-28T04:00:00.000Z"
    },
    {
        "show": "The Haunted House: The Secret of the Ghost Ball: Season 1: The Bewitched Bus!",
        "date": "2019-07-27T04:00:00.000Z"
    },
    {
        "show": "Ninja Turtles: The Next Mutation: Season 1: Unchain My Heart: Part 1",
        "date": "2019-07-27T04:00:00.000Z"
    },
    {
        "show": "The Haunted House: The Secret of the Ghost Ball: Season 1: Shinbi Apartment – Doomsday (Part One)",
        "date": "2019-07-25T04:00:00.000Z"
    },
    {
        "show": "The Haunted House: The Secret of the Ghost Ball: Season 1: The Wrath of the White-Winged Wraith",
        "date": "2019-07-25T04:00:00.000Z"
    },
    {
        "show": "The Haunted House: The Secret of the Ghost Ball: Season 1: The Unbreakable Curse of the Girl’s Hair!",
        "date": "2019-07-23T04:00:00.000Z"
    },
    {
        "show": "The Haunted House: The Secret of the Ghost Ball: Season 1: Ian the Red-Eyed Boy",
        "date": "2019-07-20T04:00:00.000Z"
    },
    {
        "show": "The Haunted House: The Secret of the Ghost Ball: Season 1: The Weird Tale of the Wicked Doll Ghost!",
        "date": "2019-07-20T04:00:00.000Z"
    },
    {
        "show": "Batman Unlimited: Monster Mayhem",
        "date": "2019-07-20T04:00:00.000Z"
    },
    {
        "show": "The Haunted House: The Secret of the Ghost Ball: Season 1: Invasion of the Iron Beast",
        "date": "2019-07-20T04:00:00.000Z"
    },
    {
        "show": "Batman Unlimited: Animal Instincts",
        "date": "2019-07-13T04:00:00.000Z"
    },
    {
        "show": "LEGO:  City: Season 1: LEGO City Compilation Special 1",
        "date": "2019-07-13T04:00:00.000Z"
    },
    {
        "show": "Room on the Broom",
        "date": "2019-07-12T04:00:00.000Z"
    },
    {
        "show": "We Bare Bears: Season 3: The Kitty",
        "date": "2019-07-10T04:00:00.000Z"
    },
    {
        "show": "We Bare Bears: Season 3: Summer Love",
        "date": "2019-07-10T04:00:00.000Z"
    },
    {
        "show": "We Bare Bears: Season 3: Road Trip",
        "date": "2019-07-10T04:00:00.000Z"
    },
    {
        "show": "Dragons: Race to the Edge: Season 1: Imperfect Harmony",
        "date": "2019-07-09T04:00:00.000Z"
    },
    {
        "show": "Dragons: Race to the Edge: Season 1: Eye of the Beholder, Part 2",
        "date": "2019-07-09T04:00:00.000Z"
    },
    {
        "show": "Dragons: Race to the Edge: Season 1: Eye of the Beholder, Part 1",
        "date": "2019-07-09T04:00:00.000Z"
    },
    {
        "show": "Spider-Man: Into the Spider-Verse",
        "date": "2019-07-02T04:00:00.000Z"
    },
    {
        "show": "Angry Birds: Season 1: Chuck Time / Where's My Crown? / Full Metal Chuck / Another Birthday / Egg Sounds / A Fork in the Friendship / Trampoline / Roughnecks",
        "date": "2019-06-26T04:00:00.000Z"
    },
    {
        "show": "LEGO Ninjago: Masters of Spinjitzu: Happy Birthday to You!",
        "date": "2019-06-22T04:00:00.000Z"
    },
    {
        "show": "PJ Masks: Season 1: Owlette and the Owletteenies / Gekko's Blame Campaign",
        "date": "2019-06-20T04:00:00.000Z"
    },
    {
        "show": "Batman Unlimited: Mechs vs Mutants",
        "date": "2019-06-18T04:00:00.000Z"
    },
    {
        "show": "Next Avengers: Heroes of Tomorrow",
        "date": "2019-06-17T04:00:00.000Z"
    },
    {
        "show": "PJ Masks: Season 1: Catboy and the Butterfly Brigade / Owlette the Winner",
        "date": "2019-06-10T04:00:00.000Z"
    },
    {
        "show": "Barbie: Spy Squad",
        "date": "2019-06-06T04:00:00.000Z"
    },
    {
        "show": "Iron Man & Captain America: Heroes United",
        "date": "2019-06-04T04:00:00.000Z"
    },
    {
        "show": "LEGO: Marvel Super Heroes: Maximum Overload",
        "date": "2019-06-04T04:00:00.000Z"
    },
    {
        "show": "Marvel Super Hero Adventures: Frost Fight!",
        "date": "2019-05-25T04:00:00.000Z"
    },
    {
        "show": "Power Rangers Ninja Steel: Season 1: Family Fusion",
        "date": "2019-05-24T04:00:00.000Z"
    },
    {
        "show": "Super Why!: Season 1: Jack and the Beanstalk & Other Story Book Adventures: The Three Little Pigs",
        "date": "2019-05-21T04:00:00.000Z"
    },
    {
        "show": "Zak Storm: Season 1 Part A: Origins Part 2",
        "date": "2019-05-18T04:00:00.000Z"
    },
    {
        "show": "Zak Storm: Season 1 Part A: Origins Part 1",
        "date": "2019-05-18T04:00:00.000Z"
    },
    {
        "show": "LEGO Marvel Super Heroes: Black Panther",
        "date": "2019-05-12T04:00:00.000Z"
    },
    {
        "show": "Super Wings: Season 1: Mongolian Stars",
        "date": "2019-04-26T04:00:00.000Z"
    },
    {
        "show": "Super Monsters Save Halloween",
        "date": "2019-04-25T04:00:00.000Z"
    },
    {
        "show": "PJ Masks: Season 1: Catboy's Flying Fiasco / Gekko's Stay-at-Home Sneezes",
        "date": "2019-04-25T04:00:00.000Z"
    },
    {
        "show": "PJ Masks: Season 1: Catboy's Tricky Ticket / Gekko and the Missing Gekko-Mobile",
        "date": "2019-04-25T04:00:00.000Z"
    },
    {
        "show": "PJ Masks: Season 1: Looking After Gekko / Catboy and the Teeny Weeny Ninjalino",
        "date": "2019-04-25T04:00:00.000Z"
    },
    {
        "show": "PJ Masks: Season 1: Owlette and the Flash Flip Trip / Catboy and the Pogo Dozer",
        "date": "2019-04-24T04:00:00.000Z"
    },
    {
        "show": "PJ Masks: Season 1: Blame It on the Train, Owlette / Catboy's Cloudy Crisis",
        "date": "2019-04-24T04:00:00.000Z"
    },
    {
        "show": "PJ Masks: Season 1: Gekko Saves Christmas / Gekko's Nice Ice Plan",
        "date": "2019-04-23T04:00:00.000Z"
    },
    {
        "show": "PJ Masks: Season 1: Catboy and the Shrinker / Owlette and the Moon-Ball",
        "date": "2019-04-23T04:00:00.000Z"
    },
    {
        "show": "PJ Masks: Season 1: Gekko and the Super Ninjalinos / Owlette's Terrible Pterodactyl Trouble",
        "date": "2019-04-23T04:00:00.000Z"
    },
    {
        "show": "Power Rangers: Megaforce: Season 1: End Game",
        "date": "2019-04-22T04:00:00.000Z"
    },
    {
        "show": "We Bare Bears: Season 3: Poppy Rangers",
        "date": "2019-04-20T04:00:00.000Z"
    },
    {
        "show": "We Bare Bears: Season 3: Subway",
        "date": "2019-04-20T04:00:00.000Z"
    },
    {
        "show": "We Bare Bears: Season 3: Panda's Art",
        "date": "2019-04-19T04:00:00.000Z"
    },
    {
        "show": "We Bare Bears: Season 3: The Demon",
        "date": "2019-04-17T04:00:00.000Z"
    },
    {
        "show": "Power Rangers: Megaforce: Season 1: Mega Mission",
        "date": "2019-04-17T04:00:00.000Z"
    },
    {
        "show": "No Good Nick: Part 1: The Catfish",
        "date": "2019-04-17T04:00:00.000Z"
    },
    {
        "show": "Power Rangers Dino Charge: Season 1: Past, Present and Fusion",
        "date": "2019-04-15T04:00:00.000Z"
    },
    {
        "show": "Power Rangers Dino Charge: Season 1: Powers from the Past",
        "date": "2019-04-15T04:00:00.000Z"
    },
    {
        "show": "Power Rangers Ninja Steel: Season 1: My Friend, Redbot",
        "date": "2019-04-15T04:00:00.000Z"
    },
    {
        "show": "Power Rangers Ninja Steel: Season 1: Drive To Survive",
        "date": "2019-04-15T04:00:00.000Z"
    },
    {
        "show": "Power Rangers Ninja Steel: Season 1: Presto-Change-O",
        "date": "2019-04-15T04:00:00.000Z"
    },
    {
        "show": "Power Rangers Ninja Steel: Season 1: Live and Learn",
        "date": "2019-04-15T04:00:00.000Z"
    },
    {
        "show": "Spy Kids 3: Game Over",
        "date": "2019-04-14T04:00:00.000Z"
    },
    {
        "show": "Pokémon the Series: Sun & Moon: Season 1: Sun & Moon: The Guardian’s Challenge!",
        "date": "2019-04-14T04:00:00.000Z"
    },
    {
        "show": "Danger Mouse: Season 1: Planet Of The Toilets",
        "date": "2019-04-13T04:00:00.000Z"
    },
    {
        "show": "Power Rangers Ninja Steel: Season 1: Forged In Steel",
        "date": "2019-04-13T04:00:00.000Z"
    },
    {
        "show": "Kicko & Super Speedo: Season 1: Episode 14",
        "date": "2019-04-13T04:00:00.000Z"
    },
    {
        "show": "Kicko & Super Speedo: Season 1: Episode 13",
        "date": "2019-04-13T04:00:00.000Z"
    },
    {
        "show": "Kicko & Super Speedo: Season 1: Episode 12",
        "date": "2019-04-13T04:00:00.000Z"
    },
    {
        "show": "Power Rangers Ninja Steel: Season 1: Return of the Prism",
        "date": "2019-04-11T04:00:00.000Z"
    },
    {
        "show": "PJ Masks: Season 1: Owlette and the Moonflower / Slowpoke Gekko",
        "date": "2019-04-06T04:00:00.000Z"
    },
    {
        "show": "PJ Masks: Season 1: Owlette of a Kind / Beat the Drum, Catboy",
        "date": "2019-04-06T04:00:00.000Z"
    },
    {
        "show": "Marvel's Hulk: Where Monsters Dwell",
        "date": "2019-04-06T04:00:00.000Z"
    },
    {
        "show": "Star Wars: The Clone Wars: Season 3: Citadel Rescue",
        "date": "2019-04-05T04:00:00.000Z"
    },
    {
        "show": "Stretch Armstrong & the Flex Fighters: Season 1: Fast Times",
        "date": "2019-04-03T04:00:00.000Z"
    },
    {
        "show": "Stretch Armstrong & the Flex Fighters: Season 1: Lie Sandwich",
        "date": "2019-04-03T04:00:00.000Z"
    },
    {
        "show": "Stretch Armstrong & the Flex Fighters: Season 1: Online Presence",
        "date": "2019-04-02T04:00:00.000Z"
    },
    {
        "show": "Gnome Alone",
        "date": "2019-04-02T04:00:00.000Z"
    },
    {
        "show": "Dinotrux Supercharged: Season 3: Ankylodump Games",
        "date": "2019-04-01T04:00:00.000Z"
    },
    {
        "show": "Dinotrux Supercharged: Season 3: Crabcavator",
        "date": "2019-04-01T04:00:00.000Z"
    },
    {
        "show": "Stretch Armstrong & the Flex Fighters: Season 1: The Age of Flexarium",
        "date": "2019-04-01T04:00:00.000Z"
    },
    {
        "show": "Stretch Armstrong & the Flex Fighters: Season 1: Confessions of a Teenage Superhero",
        "date": "2019-03-31T04:00:00.000Z"
    },
    {
        "show": "LEGO:  City: Season 1: LEGO City Compilation Special 2",
        "date": "2019-03-31T04:00:00.000Z"
    },
    {
        "show": "Goosebumps: Season 1: Phantom of the Auditorium",
        "date": "2019-03-31T04:00:00.000Z"
    },
    {
        "show": "Goosebumps: Season 1: It Came from Beneath the Kitchen Sink",
        "date": "2019-03-31T04:00:00.000Z"
    },
    {
        "show": "Ninja Turtles: The Next Mutation: Season 1: Like Brothers",
        "date": "2019-03-23T04:00:00.000Z"
    },
    {
        "show": "Coraline",
        "date": "2019-03-21T04:00:00.000Z"
    },
    {
        "show": "Scooby-Doo 2: Monsters Unleashed",
        "date": "2019-03-19T04:00:00.000Z"
    },
    {
        "show": "Ben 10: Season 1: Tomorrow Today",
        "date": "2019-03-10T05:00:00.000Z"
    },
    {
        "show": "Ben 10: Season 1: Animo Farm",
        "date": "2019-03-10T05:00:00.000Z"
    },
    {
        "show": "Ben 10: Season 1: Growing Pains",
        "date": "2019-03-10T05:00:00.000Z"
    },
    {
        "show": "Ben 10: Season 1: Take 10",
        "date": "2019-03-10T05:00:00.000Z"
    },
    {
        "show": "Ben 10: Season 1: Waterfilter",
        "date": "2019-03-09T05:00:00.000Z"
    },
    {
        "show": "Miraculous: Tales of Ladybug & Cat Noir: Season 1: Timebreaker",
        "date": "2019-03-08T05:00:00.000Z"
    },
    {
        "show": "The Epic Tales of Captain Underpants: Season 1: Captain Underpants and the Squishy Predicament of the Stanley Peet's Stinky Pits",
        "date": "2019-03-07T05:00:00.000Z"
    },
    {
        "show": "The Epic Tales of Captain Underpants: Season 1: Captain Underpants and the Terrifying Perilous Misfortune of the T.P. Mummy",
        "date": "2019-03-07T05:00:00.000Z"
    },
    {
        "show": "The Epic Tales of Captain Underpants: Season 1: Captain Underpants and the Vexing Villiany of the Vile Vimpire",
        "date": "2019-03-07T05:00:00.000Z"
    },
    {
        "show": "Spy Kids: All the Time in the World",
        "date": "2019-03-05T05:00:00.000Z"
    },
    {
        "show": "Danger Mouse: Season 1: Danger Fan",
        "date": "2019-03-04T05:00:00.000Z"
    },
    {
        "show": "Danger Mouse: Season 1: The World Wide Spider",
        "date": "2019-03-04T05:00:00.000Z"
    },
    {
        "show": "Nexo Knights: Season 1: The Book of Monsters: Part 1",
        "date": "2019-03-04T05:00:00.000Z"
    },
    {
        "show": "How the Grinch Stole Christmas",
        "date": "2019-03-04T05:00:00.000Z"
    },
    {
        "show": "Nexo Knights: The Book of Monsters: Season 2: Back to School",
        "date": "2019-03-04T05:00:00.000Z"
    },
    {
        "show": "Nexo Knights: Season 1: The Knights’ Code",
        "date": "2019-03-03T05:00:00.000Z"
    },
    {
        "show": "Spy Kids: Mission Critical: Season 1: School Dazed",
        "date": "2019-02-27T05:00:00.000Z"
    },
    {
        "show": "Incredibles 2 (Spanish Version)",
        "date": "2019-02-23T05:00:00.000Z"
    },
    {
        "show": "Voltron: Legendary Defender: Season 1: Rebirth",
        "date": "2019-02-23T05:00:00.000Z"
    },
    {
        "show": "The Dragon Prince: Season 1: Cursed Caldera",
        "date": "2019-02-23T05:00:00.000Z"
    },
    {
        "show": "We Bare Bears: Season 3: Teacher's Pet",
        "date": "2019-02-18T05:00:00.000Z"
    },
    {
        "show": "We Bare Bears: Season 3: Go Fish",
        "date": "2019-02-18T05:00:00.000Z"
    },
    {
        "show": "We Bare Bears: Season 3: I Am Ice Bear",
        "date": "2019-02-18T05:00:00.000Z"
    },
    {
        "show": "We Bare Bears: Season 3: Spa Day",
        "date": "2019-02-18T05:00:00.000Z"
    },
    {
        "show": "We Bare Bears: Season 3: Ice Cave",
        "date": "2019-02-18T05:00:00.000Z"
    },
    {
        "show": "We Bare Bears: Season 3: Pigeons",
        "date": "2019-02-18T05:00:00.000Z"
    },
    {
        "show": "LEGO DC Super Hero Girls: Brain Drain",
        "date": "2019-02-16T05:00:00.000Z"
    },
    {
        "show": "Sing-a-long with PJ Masks",
        "date": "2019-02-10T05:00:00.000Z"
    },
    {
        "show": "Ghostbusters 2",
        "date": "2019-02-10T05:00:00.000Z"
    },
    {
        "show": "Star Wars: The Clone Wars: Season 1: Trespass",
        "date": "2019-02-09T05:00:00.000Z"
    },
    {
        "show": "Star Wars: The Clone Wars: Season 4: Plan of Dissent",
        "date": "2019-02-09T05:00:00.000Z"
    },
    {
        "show": "Star Wars: The Clone Wars: Season 4: Shadow Warrior",
        "date": "2019-02-09T05:00:00.000Z"
    },
    {
        "show": "Star Wars: The Clone Wars: Season 1: Hostage Crisis",
        "date": "2019-02-09T05:00:00.000Z"
    },
    {
        "show": "Star Wars: The Clone Wars: Season 1: Jedi Crash",
        "date": "2019-02-08T05:00:00.000Z"
    },
    {
        "show": "Star Wars: The Clone Wars",
        "date": "2019-02-07T05:00:00.000Z"
    },
    {
        "show": "Indiana Jones and the Temple of Doom",
        "date": "2019-02-02T05:00:00.000Z"
    },
    {
        "show": "Bat Pat: Season 1: BFF: Bat Friends Forever / Roc of Ages",
        "date": "2019-02-02T05:00:00.000Z"
    },
    {
        "show": "The Incredibles 2",
        "date": "2019-02-02T05:00:00.000Z"
    },
    {
        "show": "Ghostbusters",
        "date": "2019-01-22T05:00:00.000Z"
    },
    {
        "show": "Sing",
        "date": "2019-01-20T05:00:00.000Z"
    },
    {
        "show": "PJ Masks: Season 1: Slow Down, Catboy!  / Gekko's Special Rock",
        "date": "2019-01-14T05:00:00.000Z"
    },
    {
        "show": "PJ Masks: Season 1: Super-Sized Gekko / Take to the Skies, Owlette",
        "date": "2019-01-14T05:00:00.000Z"
    },
    {
        "show": "We Bare Bears: Season 3: Panda 2",
        "date": "2019-01-14T05:00:00.000Z"
    },
    {
        "show": "We Bare Bears: Season 3: Vacation",
        "date": "2019-01-14T05:00:00.000Z"
    },
    {
        "show": "We Bare Bears: Season 3: The Perfect Tree",
        "date": "2019-01-13T05:00:00.000Z"
    },
    {
        "show": "We Bare Bears: Season 3: Crowbar Jones",
        "date": "2019-01-13T05:00:00.000Z"
    },
    {
        "show": "We Bare Bears: Season 3: Charlie's Halloween Thing",
        "date": "2019-01-13T05:00:00.000Z"
    },
    {
        "show": "All Hail King Julien: Exiled: Season 1: Fauxsa Unchained",
        "date": "2019-01-12T05:00:00.000Z"
    },
    {
        "show": "Trollhunters: Tales of Arcadia: Part 1: To Catch a Changeling",
        "date": "2019-01-07T05:00:00.000Z"
    },
    {
        "show": "Trollhunters: Tales of Arcadia: Part 1: Win Lose or Draal",
        "date": "2019-01-07T05:00:00.000Z"
    },
    {
        "show": "Trollhunters: Tales of Arcadia: Part 1: Becoming: Part 2",
        "date": "2019-01-05T05:00:00.000Z"
    },
    {
        "show": "Trollhunters: Tales of Arcadia: Part 1: Becoming: Part 1",
        "date": "2019-01-05T05:00:00.000Z"
    },
    {
        "show": "Super Why!: Season 1: Jack and the Beanstalk & Other Story Book Adventures: Jack and the Beanstalk",
        "date": "2019-01-01T05:00:00.000Z"
    },
    {
        "show": "New Year's Eve Countdown Collection",
        "date": "2018-12-29T05:00:00.000Z"
    },
    {
        "show": "Robocar Poli: Season 1: Please, Cleany!",
        "date": "2018-12-29T05:00:00.000Z"
    },
    {
        "show": "Robocar Poli: Season 1: The Friendship Tree",
        "date": "2018-12-29T05:00:00.000Z"
    },
    {
        "show": "Robocar Poli: Season 2: Greedy Mr. Wheeler",
        "date": "2018-12-29T05:00:00.000Z"
    },
    {
        "show": "We Bare Bears: Season 3: Private Lake",
        "date": "2018-12-28T05:00:00.000Z"
    },
    {
        "show": "We Bare Bears: Season 3: Lunch with Tabes",
        "date": "2018-12-28T05:00:00.000Z"
    },
    {
        "show": "We Bare Bears: Season 3: Citizen Tabes",
        "date": "2018-12-28T05:00:00.000Z"
    },
    {
        "show": "PJ Masks: Season 1: Catboy Takes Control  / Owlette's Two Wrongs",
        "date": "2018-12-26T05:00:00.000Z"
    },
    {
        "show": "PJ Masks: Season 1: Owlette and the Battling Headquarters / Gekko and the Mayhem at the Museum",
        "date": "2018-12-26T05:00:00.000Z"
    },
    {
        "show": "3Below: Tales of Arcadia: Part 1: Terra Incognita Part One",
        "date": "2018-12-22T05:00:00.000Z"
    },
    {
        "show": "Super Why!: Season 2: Galileo's Space Adventure & Other Stories: Galileo's Space Adventure",
        "date": "2018-12-19T05:00:00.000Z"
    },
    {
        "show": "Super Why!: Season 2: Jasper's Cowboy Wish & Other Stories: Baby Dino's Big Discovery",
        "date": "2018-12-18T05:00:00.000Z"
    },
    {
        "show": "Super Why!: Season 2: Jasper's Cowboy Wish & Other Stories: Jasper's Cowboy Wish",
        "date": "2018-12-18T05:00:00.000Z"
    },
    {
        "show": "Super Why!: Season 1: Twas the Night Before Christmas & Other stories: The Stars in the Sky",
        "date": "2018-12-08T05:00:00.000Z"
    },
    {
        "show": "Super Why!: Season 1: Twas the Night Before Christmas & Other stories: The Ghost Who Was Afraid of Halloween",
        "date": "2018-12-08T05:00:00.000Z"
    },
    {
        "show": "Super Why!: Season 1: Jack and the Beanstalk & Other Story Book Adventures: Little Red Riding Hood",
        "date": "2018-12-08T05:00:00.000Z"
    },
    {
        "show": "Despicable Me 3",
        "date": "2018-12-04T05:00:00.000Z"
    },
    {
        "show": "Super Wings: Season 1: Fish Friends",
        "date": "2018-12-02T05:00:00.000Z"
    },
    {
        "show": "Super Wings: Season 1: Rain Ride",
        "date": "2018-12-02T05:00:00.000Z"
    },
    {
        "show": "Super Wings: Season 1: Santorini Choo Choo",
        "date": "2018-12-02T05:00:00.000Z"
    },
    {
        "show": "Super Wings: Season 1: Wheel Good Time",
        "date": "2018-12-02T05:00:00.000Z"
    },
    {
        "show": "Super Wings: Season 1: Snow Ballin'",
        "date": "2018-12-02T05:00:00.000Z"
    },
    {
        "show": "Super Wings: Season 1: Miner Problem",
        "date": "2018-12-02T05:00:00.000Z"
    },
    {
        "show": "Angela's Christmas",
        "date": "2018-12-02T05:00:00.000Z"
    },
    {
        "show": "Scooby-Doo",
        "date": "2018-12-02T05:00:00.000Z"
    },
    {
        "show": "Super Wings: Season 1: Flight Fans",
        "date": "2018-12-02T05:00:00.000Z"
    },
    {
        "show": "Super Wings: Season 1: Pirate Booty",
        "date": "2018-12-02T05:00:00.000Z"
    },
    {
        "show": "Super Wings: Season 1: Pop Star",
        "date": "2018-12-02T05:00:00.000Z"
    },
    {
        "show": "Super Wings: Season 1: Follow That Ghost",
        "date": "2018-12-02T05:00:00.000Z"
    },
    {
        "show": "Super Wings: Season 1: Bubble Trouble",
        "date": "2018-12-01T05:00:00.000Z"
    },
    {
        "show": "PJ Masks: Season 1: Catboy Squared / Gekko's Super Gekko Sense",
        "date": "2018-12-01T05:00:00.000Z"
    },
    {
        "show": "PJ Masks: Season 1: Supersonic Owlette / Catboy and the Sticky Splat Slingshot",
        "date": "2018-12-01T05:00:00.000Z"
    },
    {
        "show": "Ninja Turtles: The Next Mutation: Season 1: Enemy of My Enemy",
        "date": "2018-11-30T05:00:00.000Z"
    },
    {
        "show": "Ninja Turtles: The Next Mutation: Season 1: Going Ape",
        "date": "2018-11-30T05:00:00.000Z"
    },
    {
        "show": "Ninja Turtles: The Next Mutation: Season 1: King Wick",
        "date": "2018-11-30T05:00:00.000Z"
    },
    {
        "show": "Ninja Turtles: The Next Mutation: Season 1: Sewer Crash",
        "date": "2018-11-30T05:00:00.000Z"
    },
    {
        "show": "Ninja Turtles: The Next Mutation: Season 1: All in the Family",
        "date": "2018-11-30T05:00:00.000Z"
    },
    {
        "show": "Ninja Turtles: The Next Mutation: Season 1: Meet Dr. Quease",
        "date": "2018-11-29T05:00:00.000Z"
    },
    {
        "show": "PJ Masks: Season 1: Catboy's Great Gig / Owlette's New Move",
        "date": "2018-11-28T05:00:00.000Z"
    },
    {
        "show": "PJ Masks: Season 1: Gekko Floats / Catboy's Two Wheeled Wonder",
        "date": "2018-11-28T05:00:00.000Z"
    },
    {
        "show": "Ninja Turtles: The Next Mutation: Season 1: East Meets West: Part 3",
        "date": "2018-11-28T05:00:00.000Z"
    },
    {
        "show": "PJ Masks: Season 1: Catboy and Gekko's Robot Rampage / Owlette's Feathered Friend",
        "date": "2018-11-26T05:00:00.000Z"
    },
    {
        "show": "PJ Masks: Season 1: Gekko and the Mighty Moon Problem / Clumsy Catboy",
        "date": "2018-11-26T05:00:00.000Z"
    },
    {
        "show": "Suckers: Season 1: Episode 3",
        "date": "2018-11-25T05:00:00.000Z"
    },
    {
        "show": "Suckers: Season 1: Episode 2",
        "date": "2018-11-25T05:00:00.000Z"
    },
    {
        "show": "Suckers: Season 1: Episode 1",
        "date": "2018-11-25T05:00:00.000Z"
    },
    {
        "show": "Suckers: Season 1: Episode 8",
        "date": "2018-11-25T05:00:00.000Z"
    },
    {
        "show": "Beauty and the Beast (2017)",
        "date": "2018-11-18T05:00:00.000Z"
    },
    {
        "show": "Suckers: Season 1: Episode 7",
        "date": "2018-11-18T05:00:00.000Z"
    },
    {
        "show": "Suckers: Season 1: Episode 6",
        "date": "2018-11-18T05:00:00.000Z"
    },
    {
        "show": "Suckers: Season 1: Episode 5",
        "date": "2018-11-18T05:00:00.000Z"
    },
    {
        "show": "Suckers: Season 1: Episode 4",
        "date": "2018-11-18T05:00:00.000Z"
    },
    {
        "show": "Robocar Poli: Season 1: Hide and Seek",
        "date": "2018-11-17T05:00:00.000Z"
    },
    {
        "show": "Robocar Poli: Season 1: Remember, Max!",
        "date": "2018-11-17T05:00:00.000Z"
    },
    {
        "show": "Mother Goose Club: Season 1: Cartoons with Characters",
        "date": "2018-11-17T05:00:00.000Z"
    },
    {
        "show": "The Boss Baby: Back in Business: Season 2: As the Diaper Changes",
        "date": "2018-11-07T05:00:00.000Z"
    },
    {
        "show": "Robocar Poli: Season 1: Concrete Fuss",
        "date": "2018-11-06T05:00:00.000Z"
    },
    {
        "show": "Robocar Poli: Season 1: SchoolB’s Present",
        "date": "2018-11-06T05:00:00.000Z"
    },
    {
        "show": "Robocar Poli: Season 1: Rescue Team of Broom’s Town",
        "date": "2018-11-06T05:00:00.000Z"
    },
    {
        "show": "Cars Toon: Mater's Tall Tales",
        "date": "2018-11-04T04:00:00.000Z"
    },
    {
        "show": "Trolls Holiday Special",
        "date": "2018-11-03T04:00:00.000Z"
    },
    {
        "show": "The Gruffalo",
        "date": "2018-10-30T04:00:00.000Z"
    },
    {
        "show": "Little Baby Bum: Nursery Rhyme Friends: Season 1: Episode 3",
        "date": "2018-10-29T04:00:00.000Z"
    },
    {
        "show": "Larva Island: Season 1: Mango",
        "date": "2018-10-29T04:00:00.000Z"
    },
    {
        "show": "Little Baby Bum: Nursery Rhyme Friends: Season 1: Episode 1",
        "date": "2018-10-29T04:00:00.000Z"
    },
    {
        "show": "An American Tail",
        "date": "2018-10-29T04:00:00.000Z"
    },
    {
        "show": "Tayo the Little Bus: Season 2: The Treasure Is Mine! / Rogi the Detective!",
        "date": "2018-10-27T04:00:00.000Z"
    },
    {
        "show": "Tayo the Little Bus: Season 2: Nana Visits the City / Nuri's Worst Day",
        "date": "2018-10-27T04:00:00.000Z"
    },
    {
        "show": "Tayo the Little Bus: Season 2: Please Pick Me / A New Playground!",
        "date": "2018-10-27T04:00:00.000Z"
    },
    {
        "show": "Tayo the Little Bus: Season 2: Gani the Teacher! / I'll Help You, Big",
        "date": "2018-10-27T04:00:00.000Z"
    },
    {
        "show": "Super Wings: Season 1: Samba Spectacular",
        "date": "2018-10-27T04:00:00.000Z"
    },
    {
        "show": "Super Wings: Season 1: Race Against Time",
        "date": "2018-10-27T04:00:00.000Z"
    },
    {
        "show": "Mother Goose Club: Season 1: Jump Up and Rhyme",
        "date": "2018-10-03T04:00:00.000Z"
    },
    {
        "show": "Chuggington: Season 1: Eddie Finds Time / Brewster Knows Best",
        "date": "2018-10-03T04:00:00.000Z"
    },
    {
        "show": "Chuggington: Season 1: Can't Catch Koko / Wilson and the Elephant",
        "date": "2018-10-03T04:00:00.000Z"
    }
]
